LICENSE.txt
MANIFEST.in
README.rst
buildout.cfg
setup.py
bob/__init__.py
bob.paper.ICB2015.egg-info/PKG-INFO
bob.paper.ICB2015.egg-info/SOURCES.txt
bob.paper.ICB2015.egg-info/dependency_links.txt
bob.paper.ICB2015.egg-info/entry_points.txt
bob.paper.ICB2015.egg-info/namespace_packages.txt
bob.paper.ICB2015.egg-info/not-zip-safe
bob.paper.ICB2015.egg-info/requires.txt
bob.paper.ICB2015.egg-info/top_level.txt
bob/paper/__init__.py
bob/paper/ICB2015/__init__.py
bob/paper/ICB2015/evaluate.py
bob/paper/ICB2015/execute.py