Metadata-Version: 1.1
Name: bob.paper.ICB2015
Version: 2.0.0a0
Summary: Running the experiments as given in paper: "On the Vulnerability of Palm Vein Recognition to Spoofing Attacks".
Home-page: https://github.com/bioidiap/bob.paper.ICB2015
Author: Pedro Tome
Author-email: pedro.tome@idiap.ch
License: LICENSE.txt
Platform: UNKNOWN
Classifier: Framework :: Bob
Classifier: Development Status :: 4 - Beta
Classifier: Intended Audience :: Science/Research
Classifier: License :: OSI Approved :: GNU General Public License v3 (GPLv3)
Classifier: Natural Language :: English
Classifier: Programming Language :: Python
Classifier: Environment :: Console
Classifier: Topic :: Scientific/Engineering
